code_buddy/__init__.py
code_buddy/main.py
code_buddy_assist-0.6.2.dist-info/METADATA
code_buddy_assist-0.6.2.dist-info/WHEEL
code_buddy_assist-0.6.2.dist-info/entry_points.txt
code_buddy_assist-0.6.2.dist-info/top_level.txt
code_buddy_assist-0.6.2.dist-info/RECORD
