Metadata-Version: 2.1
Name: code-buddy-assist
Version: 0.6.2
Summary: A command-line coding assistant using LLMs
Home-page: https://github.com/mmcc007/code-buddy-assist
Author: Maurice McCabe
Author-email: mmcc007@gmail.com
Classifier: Programming Language :: Python :: 3
Classifier: License :: OSI Approved :: MIT License
Classifier: Operating System :: OS Independent
Requires-Dist: GitPython
